simple_dag_editor/__init__.py
simple_dag_editor/app_builder_view.py
simple_dag_editor/auth.py
simple_dag_editor/commons.py
simple_dag_editor/flask_admin_view.py
simple_dag_editor/simple_dag_editor.py
simple_dag_editor/utils.py
simple_dag_editor/static/css/32px.png
simple_dag_editor/static/css/40px.png
simple_dag_editor/static/css/jstree.min.css
simple_dag_editor/static/css/style.css
simple_dag_editor/static/css/throbber.gif
simple_dag_editor/static/js/ace.min.js
simple_dag_editor/static/js/jstree.min.js
simple_dag_editor/static/js/mode-python.min.js
simple_dag_editor/static/js/sweetalert2.all.min.js
simple_dag_editor/templates/index_admin.html
simple_dag_editor/templates/index_appbuilder.html
simple_dag_editor/templates/index_body.html
simple_dag_editor/templates/index_head.html
simple_dag_editor/templates/index_tail.html
simple_dag_editor-0.1.1.dist-info/LICENSE
simple_dag_editor-0.1.1.dist-info/METADATA
simple_dag_editor-0.1.1.dist-info/WHEEL
simple_dag_editor-0.1.1.dist-info/entry_points.txt
simple_dag_editor-0.1.1.dist-info/top_level.txt
simple_dag_editor-0.1.1.dist-info/RECORD
