Metadata-Version: 2.1
Name: simple-dag-editor
Version: 0.1.1
Summary: Zero configuration Airflow Dag editor
Home-page: https://github.com/ohadmata/simple-dag-editor
Author: Ohad mata
Author-email: ohadmata@gmail.com
License: Apache License, Version 2.0
Platform: UNKNOWN
Classifier: Operating System :: OS Independent
Classifier: Programming Language :: Python
Classifier: Topic :: Software Development :: Libraries :: Python Modules
Classifier: Programming Language :: Python :: 3
Classifier: Programming Language :: Python :: 3.4
Classifier: Programming Language :: Python :: 3.5
Classifier: Programming Language :: Python :: 3.6
Classifier: Programming Language :: Python :: 3.7
Classifier: Programming Language :: Python :: 3.8
License-File: LICENSE
Requires-Dist: apache-airflow
